peg_this/__init__.py
peg_this/peg_this.py
peg_this/features/__init__.py
peg_this/features/audio.py
peg_this/features/batch.py
peg_this/features/convert.py
peg_this/features/crop.py
peg_this/features/inspect.py
peg_this/features/join.py
peg_this/features/trim.py
peg_this/utils/__init__.py
peg_this/utils/ffmpeg_utils.py
peg_this/utils/ui_utils.py
peg_this-3.0.6.dist-info/licenses/LICENSE
peg_this-3.0.6.dist-info/METADATA
peg_this-3.0.6.dist-info/WHEEL
peg_this-3.0.6.dist-info/entry_points.txt
peg_this-3.0.6.dist-info/top_level.txt
peg_this-3.0.6.dist-info/RECORD
