Metadata-Version: 2.4
Name: peg_this
Version: 3.0.6
Summary: A powerful, intuitive command-line video editor suite, built on FFmpeg.
Author-email: Hariharen S S <thisishariharen@gmail.com>
Project-URL: Homepage, https://github.com/hariharen9/ffmpeg-this
Project-URL: Bug Tracker, https://github.com/hariharen9/ffmpeg-this/issues
Project-URL: Releases, https://github.com/hariharen9/ffmpeg-this/releases
Classifier: Programming Language :: Python :: 3
Classifier: License :: OSI Approved :: MIT License
Classifier: Operating System :: OS Independent
Classifier: Topic :: Multimedia :: Video :: Conversion
Classifier: Topic :: Multimedia :: Video :: Non-Linear Editor
Requires-Python: >=3.8
License-File: LICENSE
Requires-Dist: ffmpeg-python==0.2.0
Requires-Dist: questionary>=2.0.0
Requires-Dist: rich>=13.0.0
Requires-Dist: Pillow>=9.0.0
Dynamic: license-file
